dizest/__init__.py
dizest/cmd.py
dizest/serve.py
dizest/version.py
dizest/workflow.py
dizest/api/__init__.py
dizest/api/runner.py
dizest/api/binding/__init__.py
dizest/api/binding/drive.py
dizest/api/binding/flow.py
dizest/api/binding/workflow.py
dizest/base/__init__.py
dizest/base/binding.py
dizest/base/config.py
dizest/base/render.py
dizest/base/spawner.py
dizest/bundle/config/boot.py
dizest/bundle/config/dizest.py
dizest/bundle/config/service.py
dizest/bundle/plugin/core/.gitignore
dizest/bundle/plugin/core/plugin.json
dizest/bundle/plugin/core/shortcut.ts
dizest/bundle/plugin/core/app/ide/api.py
dizest/bundle/plugin/core/app/ide/app.json
dizest/bundle/plugin/core/app/ide/service.ts
dizest/bundle/plugin/core/app/ide/view.pug
dizest/bundle/plugin/core/app/ide/view.scss
dizest/bundle/plugin/core/app/ide/view.ts
dizest/bundle/plugin/core/app/setting/api.py
dizest/bundle/plugin/core/app/setting/app.json
dizest/bundle/plugin/core/app/setting/view.pug
dizest/bundle/plugin/core/app/setting/view.scss
dizest/bundle/plugin/core/app/setting/view.ts
dizest/bundle/plugin/core/app/status/api.py
dizest/bundle/plugin/core/app/status/app.json
dizest/bundle/plugin/core/app/status/view.pug
dizest/bundle/plugin/core/app/status/view.scss
dizest/bundle/plugin/core/app/status/view.ts
dizest/bundle/plugin/core/app/widget.loading/app.json
dizest/bundle/plugin/core/app/widget.loading/view.pug
dizest/bundle/plugin/core/app/widget.loading/view.scss
dizest/bundle/plugin/core/app/widget.loading/view.ts
dizest/bundle/plugin/core/app/widget.tree/app.json
dizest/bundle/plugin/core/app/widget.tree/view.pug
dizest/bundle/plugin/core/app/widget.tree/view.scss
dizest/bundle/plugin/core/app/widget.tree/view.ts
dizest/bundle/plugin/core/editor/ide/api.py
dizest/bundle/plugin/core/editor/ide/app.json
dizest/bundle/plugin/core/editor/ide/view.pug
dizest/bundle/plugin/core/editor/ide/view.scss
dizest/bundle/plugin/core/editor/ide/view.ts
dizest/bundle/plugin/core/editor/monaco/api.py
dizest-4.0.15.dist-info/LICENSE
dizest-4.0.15.dist-info/METADATA
dizest-4.0.15.dist-info/WHEEL
dizest-4.0.15.dist-info/entry_points.txt
dizest-4.0.15.dist-info/top_level.txt
dizest-4.0.15.dist-info/RECORD
