Metadata-Version: 2.1
Name: dizest
Version: 4.0.15
Summary: season dizest: data management platform
Home-page: https://github.com/season-framework/dizest
Author: proin
Author-email: proin@season.co.kr
License: MIT
Classifier: License :: OSI Approved :: MIT License
Requires-Python: >=3.8
License-File: LICENSE
Requires-Dist: argh
Requires-Dist: python-crontab
Requires-Dist: matplotlib
Requires-Dist: psutil
Requires-Dist: requests
Requires-Dist: Pillow
Requires-Dist: numpy
Requires-Dist: pandas
Requires-Dist: pymysql
Requires-Dist: natsort
Requires-Dist: season (>=2.4.8)
Requires-Dist: peewee
Requires-Dist: libsass
Requires-Dist: bcrypt
Requires-Dist: python-socketio
Requires-Dist: python-socketio[client]
